setup.py
readlines_timeout/__init__.py
readlines_timeout.egg-info/PKG-INFO
readlines_timeout.egg-info/SOURCES.txt
readlines_timeout.egg-info/dependency_links.txt
readlines_timeout.egg-info/top_level.txt