Metadata-Version: 1.0
Name: readlines-timeout
Version: 1.0
Summary: Readlines implementation which can notify about timeouts.
Home-page: https://github.com/viraptor/readlines_timeout
Author: Stanisław Pitucha
Author-email: viraptor@gmail.com
License: MIT
Platform: UNKNOWN
